{
  "created_at": "2026-07-06T21:43:21",
  "description": "## [1.11.0-dev.1](https://github.com/PrathxmOp/Prathxm-Patches/compare/v1.10.0...v1.11.0-dev.1) (2026-07-06)\n\n### ✨ New Features\n\n* **Chess.com:** support v4.10.0 while preserving v4.9.49 compatibility ([7d0d4a9](https://github.com/PrathxmOp/Prathxm-Patches/commit/7d0d4a9bc7184af65b5fd6f48a4ac8ef47de6bda))",
  "download_url": "https://github.com/PrathxmOp/Prathxm-Patches/releases/download/v1.11.0-dev.1/patches-1.11.0-dev.1.mpp",
  "signature_download_url": "",
  "version": "1.11.0-dev.1"
}
